{
  "scan_id": "qa_20260318_225707",
  "timestamp": "2026-03-18 22:57:13 UTC",
  "quality_metrics": {
    "code_quality": {
      "score": 100,
      "total_files": 28354,
      "error_files": 0
    },
    "security": {
      "score": 0,
      "issues_found": 50
    },
    "performance": {
      "score": 95
    },
    "test_coverage": {
      "score": 100,
      "test_files": 4986
    }
  },
  "overall_score": 73,
  "recommendations": [
    
    "Address security vulnerabilities in scripts",
    
    "Continue monitoring and improvement"
  ]
}
